Metadata-Version: 2.1
Name: nonebot_plugin_csornament
Version: 0.2.0
Summary: nonebot社区插件，查询CSGO饰品
Author-Email: Sydrr0 <2562312527@qq.com>
License: MIT
Requires-Python: >=3.8
Requires-Dist: lxml>=4.9.3
Requires-Dist: bs4>=0.0.1
Requires-Dist: nonebot2>=2.0.1
Requires-Dist: httpx>=0.23.3
